shehzaib007/__init__.py
shehzaib007/math_operations.py
shehzaib007/string_operations.py
shehzaib007-0.1.0.dist-info/licenses/LICENSE
shehzaib007-0.1.0.dist-info/METADATA
shehzaib007-0.1.0.dist-info/WHEEL
shehzaib007-0.1.0.dist-info/top_level.txt
shehzaib007-0.1.0.dist-info/RECORD
