Metadata-Version: 2.4
Name: shehzaib007
Version: 0.1.0
Summary: A simple utility package with basic math and string operations
Home-page: https://github.com/yourusername/shehzaib007
Author: Shehzaib
Author-email: your_email@example.com
Project-URL: Bug Reports, https://github.com/yourusername/shehzaib007/issues
Project-URL: Source, https://github.com/yourusername/shehzaib007
Keywords: math string operations utility
Classifier: Programming Language :: Python :: 3
Classifier: Programming Language :: Python :: 3.7
Classifier: Programming Language :: Python :: 3.8
Classifier: Programming Language :: Python :: 3.9
Classifier: Programming Language :: Python :: 3.10
Classifier: Programming Language :: Python :: 3.11
Classifier: License :: OSI Approved :: MIT License
Classifier: Operating System :: OS Independent
Classifier: Development Status :: 3 - Alpha
Classifier: Intended Audience :: Developers
Classifier: Topic :: Software Development :: Libraries :: Python Modules
Requires-Python: >=3.7
License-File: LICENSE
Dynamic: author
Dynamic: author-email
Dynamic: classifier
Dynamic: description
Dynamic: description-content-type
Dynamic: home-page
Dynamic: keywords
Dynamic: license-file
Dynamic: project-url
Dynamic: requires-python
Dynamic: summary
